choam/__init__.py
choam/__main__.py
choam/choam_client.py
choam/constants.py
choam/create_setup_file.py
choam/find_dependencies.py
choam/folder_structure.py
choam/gitignore.py
Choam-1.0.2.dist-info/METADATA
Choam-1.0.2.dist-info/WHEEL
Choam-1.0.2.dist-info/entry_points.txt
Choam-1.0.2.dist-info/top_level.txt
Choam-1.0.2.dist-info/RECORD
