Metadata-Version: 2.1
Name: Choam
Version: 1.0.2
Summary: Python project scaffolder/manager
License: UNKNOWN
Project-URL: Source, https://github.com/cowboycodr/choam
Keywords: package,manager
Platform: UNKNOWN
Requires-Dist: fire
Requires-Dist: toml
Requires-Dist: twine
Requires-Dist: wheel
Requires-Dist: choam
Requires-Dist: typing
Requires-Dist: autoapi
Requires-Dist: findimports
